gl/__init__.py
gl/main.py
gitlab_command-0.1.1.dist-info/entry_points.txt
gitlab_command-0.1.1.dist-info/LICENSE
gitlab_command-0.1.1.dist-info/WHEEL
gitlab_command-0.1.1.dist-info/METADATA
gitlab_command-0.1.1.dist-info/RECORD
