Metadata-Version: 2.1
Name: gitlab-command
Version: 0.1.1
Summary: 
Author: Jason Viloria
Author-email: jason.viloria@optiscangroup.com
Requires-Python: >=3.10,<4.0
Classifier: Programming Language :: Python :: 3
Classifier: Programming Language :: Python :: 3.10
Requires-Dist: bump-pydantic (>=0.6.1,<0.7.0)
Requires-Dist: pydantic (>=2.1.1,<3.0.0)
Requires-Dist: pydantic-settings (>=2.0.2,<3.0.0)
Requires-Dist: python-gitlab (>=3.15.0,<4.0.0)
